README.md
setup.py
benefactor/__init__.py
benefactor/dicts.py
benefactor/lists.py
benefactor/memory.py
benefactor/numbers.py
benefactor/strings.py
benefactor.egg-info/PKG-INFO
benefactor.egg-info/SOURCES.txt
benefactor.egg-info/dependency_links.txt
benefactor.egg-info/top_level.txt
benefactor/tests/__init__.py
benefactor/tests/test_dicts.py
benefactor/tests/test_lists.py
benefactor/tests/test_numbers.py
benefactor/tests/test_strings.py