Metadata-Version: 2.1
Name: benefactor
Version: 0.1
Summary: Useful Python snippets
Home-page: https://github.com/viktorchukhantsev/benefactor
Author: Viktor Chukhantsev
Author-email: email@viktor.dev
License: UNKNOWN
Platform: UNKNOWN
Classifier: Programming Language :: Python :: 3
Classifier: License :: OSI Approved :: MIT License
Classifier: Operating System :: OS Independent
